django_recurrence-1.14.dist-info/METADATA
django_recurrence-1.14.dist-info/WHEEL
django_recurrence-1.14.dist-info/entry_points.txt
django_recurrence-1.14.dist-info/licenses/LICENSE
recurrence/__init__.py
recurrence/base.py
recurrence/choices.py
recurrence/compat.py
recurrence/exceptions.py
recurrence/fields.py
recurrence/forms.py
recurrence/locale/ar/LC_MESSAGES/django.mo
recurrence/locale/ar/LC_MESSAGES/django.po
recurrence/locale/ar/LC_MESSAGES/djangojs.mo
recurrence/locale/ar/LC_MESSAGES/djangojs.po
recurrence/locale/de/LC_MESSAGES/django.mo
recurrence/locale/de/LC_MESSAGES/django.po
recurrence/locale/de/LC_MESSAGES/djangojs.mo
recurrence/locale/de/LC_MESSAGES/djangojs.po
recurrence/locale/en/LC_MESSAGES/django.mo
recurrence/locale/en/LC_MESSAGES/django.po
recurrence/locale/en/LC_MESSAGES/djangojs.mo
recurrence/locale/en/LC_MESSAGES/djangojs.po
recurrence/locale/es/LC_MESSAGES/django.mo
recurrence/locale/es/LC_MESSAGES/django.po
recurrence/locale/es/LC_MESSAGES/djangojs.mo
recurrence/locale/es/LC_MESSAGES/djangojs.po
recurrence/locale/eu/LC_MESSAGES/django.mo
recurrence/locale/eu/LC_MESSAGES/django.po
recurrence/locale/eu/LC_MESSAGES/djangojs.mo
recurrence/locale/eu/LC_MESSAGES/djangojs.po
recurrence/locale/fr/LC_MESSAGES/django.mo
recurrence/locale/fr/LC_MESSAGES/django.po
recurrence/locale/fr/LC_MESSAGES/djangojs.mo
recurrence/locale/fr/LC_MESSAGES/djangojs.po
recurrence/locale/he/LC_MESSAGES/django.mo
recurrence/locale/he/LC_MESSAGES/django.po
recurrence/locale/he/LC_MESSAGES/djangojs.mo
recurrence/locale/he/LC_MESSAGES/djangojs.po
recurrence/locale/hu/LC_MESSAGES/django.mo
recurrence/locale/hu/LC_MESSAGES/django.po
recurrence/locale/hu/LC_MESSAGES/djangojs.mo
recurrence/locale/hu/LC_MESSAGES/djangojs.po
recurrence/locale/nl/LC_MESSAGES/django.mo
recurrence/locale/nl/LC_MESSAGES/django.po
recurrence/locale/nl/LC_MESSAGES/djangojs.mo
recurrence/locale/nl/LC_MESSAGES/djangojs.po
recurrence/locale/pt_BR/LC_MESSAGES/django.mo
recurrence/locale/pt_BR/LC_MESSAGES/django.po
recurrence/locale/pt_BR/LC_MESSAGES/djangojs.mo
recurrence/locale/pt_BR/LC_MESSAGES/djangojs.po
recurrence/locale/sk/LC_MESSAGES/django.mo
django_recurrence-1.14.dist-info/RECORD
