Metadata-Version: 2.1
Name: django-recurrence
Version: 1.14
Summary: Django utility wrapping dateutil.rrule
Author-Email: Tamas Kemenczy <tamas.kemenczy@gmail.com>, Lino Helms <lino@lino.io>
License: BSD
Classifier: Development Status :: 5 - Production/Stable
Classifier: Environment :: Plugins
Classifier: Environment :: Web Environment
Classifier: Framework :: Django
Classifier: Framework :: Django
Classifier: Framework :: Django :: 4.2
Classifier: Framework :: Django :: 5.2
Classifier: Framework :: Django :: 6.0
Classifier: Intended Audience :: Developers
Classifier: License :: OSI Approved :: BSD License
Classifier: Operating System :: OS Independent
Classifier: Programming Language :: Python
Classifier: Programming Language :: Python :: 3
Classifier: Programming Language :: Python :: 3.10
Classifier: Programming Language :: Python :: 3.11
Classifier: Programming Language :: Python :: 3.12
Classifier: Programming Language :: Python :: 3.13
Classifier: Programming Language :: Python :: Implementation
Classifier: Programming Language :: Python :: Implementation :: CPython
Classifier: Programming Language :: Python :: Implementation :: PyPy
Project-URL: Homepage, https://github.com/jazzband/django-recurrence
Requires-Python: >=3.9
Requires-Dist: django>=4.0
Requires-Dist: python-dateutil
